{
  "job_id": "JD_001",
  "title": "Senior Backend Engineer (Python)",
  "company": "TechViet Solutions",
  "requirements": {
    "skills": [
      "Python",
      "Django or FastAPI",
      "PostgreSQL",
      "Redis",
      "Docker",
      "AWS",
      "REST API",
      "Microservices",
      "Git"
    ],
    "min_years_experience": 4,
    "key_responsibilities": [
      "Design and build REST APIs using Django or FastAPI",
      "Develop and maintain microservices with proper observability",
      "Optimize PostgreSQL queries and schema performance",
      "Deploy and operate services on AWS (EC2/S3/RDS/Lambda)",
      "Implement caching and messaging with Redis (and optionally RabbitMQ)",
      "Conduct code reviews, lead technical discussions, and mentor juniors"
    ],
    "min_education": "Bachelor"
  }
}