{
  "id": "cv (1862).pdf",
  "normalized_sections": {
    "ABOUT": "resume\na.noorul ameen\ncontact : 918098360830\nemail : noorulameen302 gmail.com\nto support the growth and success of your organization that provides challenge,\nencourages advancement, and rewards achievement with the opportunity to utilize my\nsubstantial experience, , and proven abilities in my teaching profession.\nprofessional and acadamic qualifications:\nqualification\ninstitute/university\nyear of passing\npercentage\nmohamed sathak polytechnic\n2017\ndiploma in\n70%",
    "EDUCATION": {
      "raw": "college, kilakarai.",
      "degree": [],
      "institution": [
        "college"
      ],
      "years": []
    },
    "PROJECTS": {
      "raw": "mechanical\nengineering\nmohamed sathak private\n2015\n75.9%\nindustrial training institute,\ni.t.i\nkilakarai.\n(fitter)\nlanguages known: english tamil elemination of co2 particles in exhaust gas.\ncomputer skils: working knowledge of windows and internet. and familiar with ms-\nword / ms-excel.\nattended courses certificate:",
      "keywords": []
    },
    "SKILLS": [
      "247 pallivasal street",
      "a.noorul ameen",
      "age : 23",
      "as well as individually.",
      "attended a lima course for 2 years.",
      "attended the auto cad course for 3 months",
      "attended the auto mobile course and having certificate",
      "can work effectively in team",
      "date :",
      "date of birth : 25-02-1995",
      "declaration:",
      "easily negotiate with other people.",
      "father s name : a.abdul basith sait",
      "good listener and quick learner.",
      "hardworking.",
      "have high level of persuasiveness.",
      "hobbies : internet surfing",
      "i hereby declare that above-mentioned information is correct up to my",
      "india.",
      "knowledge and i bear the responsibility for the correctness of the above mentioned",
      "marital status : single",
      "mudukulathur ( taluk )",
      "nationality : indian",
      "particulars.",
      "passport no : p5543555",
      "personal address:",
      "personal information:",
      "personal skils:",
      "place :",
      "positive attitude",
      "ramanathapuram ( dist)",
      "reading news papper etc",
      "sex : male",
      "strength : confident",
      "tamilnadu.",
      "theriruveli (post) 623711",
      "your s faithfully"
    ]
  }
}