{
  "id": "cv (1507).pdf",
  "normalized_sections": {
    "ABOUT": "sudharajesh3691 gmail.com 91-7358421116\ngraphic designer\nraghasudha rajesh\nadobe photoshop, adobe coreldraw\nadobe illustrator, adobe indesign\ndesign or create graphics to meet specific commercial or promotional needs,\nsuch as packaging, displays, or logos. use a variety of mediums to achieve artistic\nor decorative effects. be part of a dynamic and innovative team of designers in\ngenerating top-notched designs that delight customers.\nprofessional expertise\ngood knowledge in logo creation, brochure and booklets creation, newsletter and advertisement creations\ngood knowledge in web designing using photoshop",
    "WORK EXPERIENCE": {
      "raw": "ability to bring fresh perspective to the brand without losing original intent. excellent team player and ability to work in groups to complete a desired task\nunderstanding the business requirements company\nposition\nwork period\nbleap strategic\ngraphic designer\njan2018 till date\nmarketing & brand\nconsultants\noppo mobile pvt ltd\ngraphic designer\ndec2016 october 2017",
      "companies": [
        "company",
        "ltd",
        "pvt"
      ],
      "titles": [],
      "years": [
        "20"
      ]
    },
    "SKILLS": [
      "(freelancer)graphic",
      "03-06-1991",
      "10thstdinstitution board",
      "16th street",
      "60",
      "75",
      "a manner that lends dignity to the organization and worthy enough of the",
      "address",
      "adobe coreldraw",
      "adobe dreamweaver",
      "adobe illustrator",
      "adobe indesign",
      "adobe photoshop",
      "age",
      "arasu engineering college at",
      "at kumbakonam",
      "august 2013 september 2014",
      "b.e (cse)",
      "certificate in digital",
      "chennai",
      "chennai 600061.",
      "college",
      "date of birth",
      "date:",
      "declaration",
      "design course",
      "designer",
      "diploma(cse)",
      "door no:f",
      "educational details",
      "english",
      "enize technologies",
      "ganga nagar",
      "graphic designer",
      "graphicdesigner",
      "html",
      "husband name",
      "i hereby solemnly affirm that all the details provided above are true to",
      "i shall carry myself in",
      "image infotainment limited",
      "july2015 november2015",
      "kumbakonam",
      "languages known :",
      "march 2016 august 2016",
      "na",
      "palavanthangal",
      "percent",
      "person.",
      "personal details",
      "place: chennai",
      "ponnaiyahramajayam polytechnic college",
      "publishers",
      "qualification",
      "ragunatham flats",
      "rajesh.s",
      "rr donnelley",
      "school",
      "school at kumbakonam",
      "software",
      "sri saraswathipadasala higher secondary",
      "sudharajesh3691 gmail.com 91-7358421116",
      "tamil",
      "the best of my knowledge and belief and that at all times",
      "thillai",
      "united global",
      "v.raghasudha rajesh",
      "yours truly"
    ]
  }
}