{
  "id": "cv (1304).pdf",
  "normalized_sections": {
    "PROJECTS": {
      "raw": "preparation of zns nanoparticles using microwaves assisted synthesis: effects of the\ncarbothermal reduction of silica using microwaves as an energy source. ampere 10th\nmagnesia spinels using microwaves as energy source. idem. pp. 104-107\nreduction of iron oxides using microwaves as power source. idem. pp. 423-428",
      "keywords": []
    },
    "WORK EXPERIENCE": {
      "raw": "microwave and radio frequency applications. austin, tx, usa (nov. 2004).\ninstitute montreal, canad . jul. 2000, pp. 72-74\nmicrowave power institute, washington, dc. jul. 1999, pp. 5-8\ninternational microwave power institute, chicago, ill. jul. 1998, pp. 47-50\npower symposium, international microwave power institute, ottawa, canad . jul.\npower institute, boston ma. jul. 1996 pp. 100-103\nbeam processing of advanced materials, tms/asm cle. oh. oct. 1995, pp.261-268\nmateriales, instituto tecnol gico de saltillo, nov. 2000, pp. 338-345\nesiqie, ipn, may.1996, pp. 362-367\nnacional de siderurgia, instituto tecnol gico de morelia morelia, mich. nov. 1995,",
      "companies": [],
      "titles": [
        "intern"
      ],
      "years": [
        "19",
        "20"
      ]
    },
    "EDUCATION": {
      "raw": "microwave power institute, toronto, canad . 13-17 julio, 2004\ninternational microwave power institute impi (tesorero 2007-2010)",
      "degree": [],
      "institution": [
        "institute"
      ],
      "years": [
        "20"
      ]
    }
  }
}