{
  "id": "cv (4745).pdf",
  "normalized_sections": {
    "ABOUT": "information technology specialist i\naccount management, cables, cabling, help desk, linux, ms exchange server, sharepoint, network security, desktop support, unix, hp unix,\nvbscript, visual basic programming, windows server\nactive directory account management, help desk, linux, ms exchange server 2010, network/server security, desktop support, unix, windows\nserver, geographic information system, group policy scom & sccm, vbscripts and powershell, sans,\nactive directory account management and troubleshooting, help desk, linux, ms exchange server 2010, network/server security, desktop\nsupport, unix, windows server, geographic information system, group policy scom & sccm, vbscripts and powershell, sans,\nwork history\ninformation technology specialist i\n07/2008 to current\ncomputer network specialist company name city , state\ni serve as the lan administrator.\ni installed and maintain over 100 servers.\ni installed and maintain a hyper v cluster of 9 nodes.\ni administer several systems including exchange 2010, lync 2013, active directory 2012 including user accounts & group policy,\nmicrosoft system center and operations manager 2012, proofpoint spam filter and iboss web filter, arcgis.\ni manage active directory user accounts and troubleshoot active directory replication issues when necessary.\ni maintain 3 sans including nimble, dell equallogic and storsimple.\ni assisted with selecting alertus desktop alerting system by watching vendor demonstrations and recommending the best alerting system for\nour environment.\ni work with users on high level technical issues to analyze issue sand then take corrective action.\ni perform new employee technology orientations and cellphone training in groups or individually.\ni write or modify scripts such as powershell, vbscript.",
    "SKILLS": [
      "week long course emc networker week long course arcgis week long course windows 2012 - powershell week long course :"
    ],
    "WORK EXPERIENCE": {
      "raw": "i administer a vsphere server.\n06/2001 to 07/2008\ntechnology specialist iii company name city , state\ninstall and configure hp network switches, program switch ports and assign vlans, connect network wall ports and terminate network\ncables when necessary, troubleshoot network port communication errors and take appropriate action to correct problems, utilize tcp/ip\nutilities such as ping, tracert and ipconfig to diagnose network problems, installed and maintain whats up network device connectivity\nmonitoring software and configured the program to send sms messages when a device or service goes down, installed and maintained\nblackberry enterprise server for ms exchange server, fedora core linux with multi router traffic grapher, 2 windows 2003 domain\ncontrollers, renaissance learning and read 180 servers, xiotech san and tnt network security appliance, written a number of dos and\nvbscript scripts to automate many functions, including student user account creation by exporting data from the student information system\nformatting the export file and to create approximately 5000 student user accounts, create home folders and set permissions, utilized group\npolicy to secure workstations or install new software, implemented the district geographic information system by recommending arcgis\nsoftware to my manager and worked with city and county agencies to acquire base layers and created additional layers such as school sites\nand attendance areas, communicated with teachers, managers and students, installed and supported a variety of software including anti virus,\ncomputers when necessary.\nlan administrator\ninstall and manage hyper v and other servers manage 3 sans - dell equallogic, nimble & storsimple troubleshooting server and client\nissues administer exchange 2010, proofpoint spam filter, iboss web filter, system center operations manager and operation manager.\nemc networker backup installed and maintain active directory, group policy, user account management analyzing technical issues to\nimprove functio9nality software/operating systems: windows server 2016, 2012, 2003, 2000, windows xp, 7, 10, linux hp unix,\nmicrosoft office 2007, 2010, 2013, 2016, skype for business, track it work orders, escape financial system, aeries student information\nsystem, alertus desktop alerting, , laserfiche, sharepoint 2013, lync 2013 iboss web filter, proofpoint spam filter, exchange 2010\ndag and client access array, informacast speaker system,microsoft system center and operations manager, emc networker backup\nsoftware, arcgis desktop and server, maas360 mobile phone management, azure hardware: install components such as network\ninterface cards, ram, video cards, hard drives, raid controllers, network cabling, motherboards, power supplies also troubleshooting\ncomponents.\n2013\ni have attended several college computer science courses. this includes visual basic programming, unix, several networking courses exchange :",
      "companies": [
        "company",
        "inc"
      ],
      "titles": [
        "manager"
      ],
      "years": [
        "20"
      ]
    }
  }
}