{
  "id": "cv (2120).pdf",
  "normalized_sections": {
    "ABOUT": "v.vinothkumar\nm.tech industrial safety engineering\nemail : vinothveereswaran04 gmail.com\nmobile: 91- 9787329907\nto work with dedication in a challenging and rewarding environment that gives me job\nsatisfaction, which helps me to sharpen my and acquire new ones.\neducational qualification:\nmarks\ndegree\ninstitution\nyear of study\nobtained\nkalasalingam university,\nm.tech industrial\nkrishnankoil,\n2015- 2017\ncgpa : 7.48\nsafety engg\nvirudhunagar (dt).\nkalasalingam university,\nb.tech mechanical\nkrishnankoil,\n2011-2015\ncgpa : 6.6\nengineering\nvirudhunagar (dt).\nworkshop attended:\nindustries at m.kumarasamy college of engineering karur.\nat university college of engineering villupuram.\ntechnical qualification: quick learner, adapting easily to new protocols and changing environments\ndate of birth\n: 03-02-1994\nsex\n: male\nnationality\n: indian\nlanguages known : tamil, english, kannada (speak)\nfather s name : mr.v.veereswaran\npermanent address : 11-05-25, west street, kariyanampatty, pannaipuram\ntheni (dist.)-625524.\ndeclaration:\ni hereby acknowledge that all the information given above is true to the best of my\nknowledge.\ndate:\nplace:\n(vinothkumar v)",
    "PROJECTS": {
      "raw": "s.u.m.higher secondary school,\nhsc\nrayappanpatty,\n2009-2011\n80%\ntheni (dt).\ngovernment higher secondary\nschool,\nsslc\n2007-2009\n86%\npannaipuram,\ntheni (dt).\narea of interest: ergonomics fire & safety engineering construction safety\nindustrial visit: fertilizers and chemicals travancore limited (fact), cochin. zf wind power private limited kovai. dcw chemical industry tuticorin.\ngear box in quality, environmental & safety at zf wind power coimbatore\nprivate limited.\ntvs brakes india private limited sholighur at vellore (dt).",
      "keywords": [
        "app"
      ]
    },
    "SKILLS": [
      "ability to deal with people diplomatically",
      "analyzing capacity",
      "and manage",
      "coimbatore (may 2016 aug 2016)",
      "comprehensive problem solving abilities.",
      "contractor managements system",
      "costs to meet corporate objectives",
      "develop safety incentive programs",
      "guidance and technical support for hse issues",
      "implement programs to effectively reduce risk",
      "increase safety awareness",
      "internship:",
      "irca approved internal auditor for ohsas 18001:2007 certified by dnv-gl.",
      "provide leadership",
      "risk assessment",
      "safety audit",
      "safety inspection & observation",
      "sound knowledge of hse management &control",
      "tasking.",
      "theme based audits",
      "zf wind power coimbatore private limited"
    ]
  }
}