{
  "id": "cv (957).pdf",
  "normalized_sections": {
    "WORK EXPERIENCE": {
      "raw": "gilbert muniz, hairstylist\nwww.cloutierremix.com/gilbertmuniz\ncelebrities\nabigail spencer\neliza dushku\nmichelle borth\nrobin thicke\nalison brie\npaz vega\nmike white\ntorrey devitto\nallie gonino\njamie-lynn sigler\nmiranda lambert\ntricia helfer\nandrea rosen\njonathan bennett\nmolly qinn\nvanessa villela\nchina anne mcclain\nlaura vandervoort\nmolly shannon\nzoe kravitz\ndaniella alonso\nmia rose frampton\nrachel boston\neditorial\ncosmopolitan german\nelle - canada\ngenlux\nline magazine\ncrystal magazine\nla magazine\nsilvia magazine\nadvertising\npeta\nbahamas superbowl\nphotographers\nandrew matusik\ngiuliano bekor\njonny vasic\npatrick demarchelier\nandrew mcleod\njoe pugliese\nlucas grossi\ntony kelly\n2632 la cienega avenue los angeles, california 90034 310. 839. 8722 cloutierremix.com",
      "companies": [],
      "titles": [],
      "years": []
    }
  }
}