{
  "id": "cv (2176).pdf",
  "normalized_sections": {
    "ABOUT": "curriculum vitae\ng.angamuthu\n14/16 ayyanar koil street,\npoovalur (po), lalgudi (tk), trichy (dt),\ntamilnadu, india.\ncontact no: 9789635413, 9962816791, and 6380073421\ne-mail : guruu muthuu yahoo.com\nskype id :muthucivil1999\nto obtain a challenging post an organization with of responsibilities this would utilize my and knowledge.\nto work in a congenial and challenging atmosphere and achieve a successful career.\ncapability & strength:\ngood communication and interpersonal management . sincere, hardworking and have strong commitments. to make the work schedule for concrete works as well as excavation for pipeline trenches. to make the daily cost & revenue report and submit to manager and also preparing daily work progress report to client\nto make the daily cost & revenue report and submit to manager and also preparing daily work progress report to client\nco-ordinate the with engineers and planning, preparing daily progress of work making daily and monthly report of the of construction manager page 6 of 8\nto plan & schedule for the next day work and co-ordinate with qa/qc, survey, mechanical &\nsafety department to do the work\nname\n:\nangamuthu.g\ndate of birth\n:\n28.06.1980\nmarital status\n:\nmarried\nnationality\n:\nindian\npassport number\n:\nn6947078\npassport validity : 08.03.2026\npermanent address",
    "WORK EXPERIENCE": {
      "raw": "interested in learning and involving in new areas. belief in teamwork. ability to educate and encourage subordinates. ability to solve engineering problems. april 1999 august 2005, m/s c.s.promoters srirangam, trichy, tamilnadu\nsite engineer",
      "companies": [],
      "titles": [
        "engineer"
      ],
      "years": [
        "19",
        "20"
      ]
    },
    "PROJECTS": {
      "raw": "construction of multistoried residential building construction of individual luxurious villas and bungalows. tasks within this role included:\nmanage and monitor the actual performance of the structural and architectural design during construction stage. this includes coordination of technical issues with sub contractors and internal\ntechnical support units.\ncoordination with both the manager and consultant to establish the change requirements and ensure effects of ongoing amendments to the design are advised to all parties.\nchairing of subcontractor meetings to ensure material delivery schedules, programs and all outstanding actions are being completed.\nmonitoring the construction programs. coordination of clients interiors design contractor with sub contractor to ensure smooth transition of trades to facilitate the program.\npage 1 of 8\nprovide monthly technical reports to lead architects and superiors. calculate material requirements and arrangements. arranging the equipments for all type works. preparing check list before pouring works and preparing the rfi (request for information) &\ninspection request.\nfinal check with consultants and modify the work as per comments. maintain the measurement book and visualize the output from the manpower.\nmake the final bill and submit to client. at the time of purchasing the material like wood, tile, bathroom fittings, electrical fittings & paint etc, consult with client and get material approval.\nfinalize the quantity of subcontractor s works and deduct the advance and weekly payment from total amount of works. in the case of some critical site work condition take the correct own\ndecision and follow that same way. such type of official work like planning department, public\nwork department, electricity board, municipality, involved those type work also.\nchecking & preparation of the sub contractor monthly bills payments for various types of works. september 2005 march 2008 rezayat company limited, al-khobar, ksa\nbuilding inspector\ni was worked in saudi arabian oil company (saudi aramco) under sponshership of\nrezayat company limited as a building inspector\nconstruction of south admin building in mubarraz aramco (ksa) construction of admin building at shedgum gas plant area (ksa) tasks within this role included:\ninspect and monitor construction sites to ensure overall compliance. measure dimension verify level, alignment, andfixtutures to ensure building compliance .\nestablish and maintain all files, submittals, daily reports and contractor report. keep daily logs, including photographs taken during inspection. monitor construction sites periodically to ensure overall compliance. inspect and monitor construction sites to ensure adherence to safety standards, building codes, and specification.\nevaluate premises for cleanliness, including proper garbage disposal and lack of vermin infestation. establish and maintain all architects, correspondence, change orders, meeting minutes, supplemented instructions, request for information, request for changes and all correspondence between architect\nengineer, and the contractor.\ncompose and submit weekly status reports, weekly percentage completion reports, and daily reports to include conditions,temperature,weather condition, general conditions, site equipment used,\npage 2 of 8\nsubcontractors and personnel hours worked, verbal discussion, and oral instruction, phone\nconversations, visitors to site job requirements delay.\njuly 2008 july 2013 gulf turrets l.l.c. dubai, u.a.e\nsite engineer\nconstruction of (g 1)10 villas at dubai, uae. construction of chemical defence centre-2(construction of senior and junior accommodations buildings g 2 , construction of chemical store with high ceiling, and\nco-ordinate with plumbing and drainage works for all the facilities) at zayed military\ncity al-ain, uae\nconstruction of boat garage, heavy equipment store, office building and senior accommodation building and car parking works, and asphalt road works at shahama\nmilitary abuhabi, uae\nconstruction of special building at shahama military abudhabi, uae reconstruction of bright point hospital g 14 at abudhabi, construction of rest room building at mountain top near communication tower area at ras-al-khaimah, uae\nconstruction of sensor ttower (cnia tower ) works in onshore at jebel dhana , abudhabi uae\nconstruction of sensor tower ( cnia tower ) work in offshore at arzanah island, abudhabi uae\ntasks within this role included:\nheading the specified execution team from mobilization to demobilization for the assigned job till completion of the .\nregular inspection of materials delivered to site and maintenance of record. responsible for day to day",
      "keywords": [
        "app"
      ]
    },
    "EDUCATION": {
      "raw": ":\nno, 14/16 ayyanar koil street,\npoovalur post,\nlalgudi taluk, trichy district,\ntamilnadu, india 621 712.\ncontact phone number\n: 91-9962816791 91-9789635413 91-6380073421\nlanguages known\n:\ntamil & english, hindi\ndriving license\n:\nindia valid license\nprofessional qualification\ninstitute: government polytechnic, tiruchirappalli tamilnadu\npage 7 of 8\nbachelor of technology civil engineering doing from jrn vidyapeeth (deemed-to-be) university\nfrom 2013 - 2017\ncomputer proficiency\nms word, ms excel, ms powerpoint, and auto cad. page 8 of 8",
      "degree": [
        "bachelor"
      ],
      "institution": [
        "institute",
        "university"
      ],
      "years": [
        "20"
      ]
    },
    "ACTIVITIES": "on site, maintenance of daily report and reporting to manager daily.\nexecution of the as specified in the approved site execution plan, method statements and qc documents.\nco-ordination between head office and site for materials and logistics. responsible for planning of resource, assigning work and manage the team members, monitor quality and standard of work while execution, timely completion of the , implementation of health\npage 3 of 8\nand safety procedure as per the company standards, maintain documentation, co-ordination\nwith consultant, working groups, suppliers and sub-contractors to ensure quality and timely\nmay 2014 december 2014 teejan trading and contracting l.l.c. sultanate of oman\nsite engineer\nconstruction of special task force complex (mosque, and clinic building, class room building, police station, commercial block building, officers club and\naccommodations) for royal oman police (rop) work. at al-buraimi in sultanate of\noman.\ntasks within this role included:\nstudy the drawings and specification methodically. final checking of surveyors level & co-ordination points.\npreparing the work scheduling and work distribution to foremen, charge hands. making the bar bending schedules as per the consultants drawings and comments. checking all type of work like\nform works, steel fixing work, post tension work, concrete masonry works, joinery works & finishing\nworks.\ncalculate material requirements and arrangements. arranging the equipments for all type of works. preparing check list before pouring works and preparing the inspection request.\nfinal check with consultants and modify the work as per comments. maintain the measurement book and visualize the output from the manpower.\ncoordinate with subcontractors and maintain the work with quality and economy. reporting the at the time of final bill make the as built drawings, separate the variations of quantity in between and as built work. calculated and billing of breaking of the brick work and concrete\nwork because of client modification of the plan, structure, materials.\nreporting to the superior about daily work, purchase materials, requiring materials, labors, clarify the doubt of the work and merits and demerits of that day work.\nchecking & preparation of the sub contractor monthly bills payments for various types of works. page 4 of 8\nfebruary 2015 february 2016 shapoorji pallonji engineering construction chennai\nsenior engineer\nconstruction of aravind eye hospital at chennai (g 8 2basements) tasks within this role included:\nstudy the drawings and specification methodically. final checking of surveyors level & co-ordination points.\npreparing the work scheduling and work distribution to foremen, charge hands. making the bar bending schedules as per the consultants drawings and comments. checking all type of work like\nform works, steel fixing work, post tension work, concrete masonry works, joinery works & finishing\nworks.\ncalculate material requirements and arrangements. arranging the equipments for all type of works. preparing check list before pouring works and preparing the inspection request.\nfinal check with consultants and modify the work as per comments. maintain the measurement book and visualize the output from the manpower.\ncoordinate with subcontractors and maintain the work with quality and economy. reporting the at the time of final bill make the as built drawings, separate the variations of quantity in between and as built work. calculated and billing of breaking of the brick work and concrete\nwork because of client modification of the plan, structure, materials.\nreporting to the superior about daily work, purchase materials, requiring materials, labors, clarify the doubt of the work and merits and demerits of that day work.\nchecking & preparation of the sub contractor monthly bills payments for various types of works. page 5 of 8\nnovember 2016 november 2017 nexus general trading and contracting w.l.l., kuwait\nsite engineer\ncrude oil tank foundation, pipe supports, nitrogen storage tank foundation, fire water pump foundation, box culverts for road crossings, substation building, inlet manifold foundation,\nair handling unit foundation, light pole foundations, equipment foundations, pipe sleepers,\nincinerator tank foundation, incinerator blower foundations at heavy oil production facility\nin umm niqa (15049) kuwait oil company(k.s.c.)\nlocal equipment room foundation, pipe sleepers, pipe supports,evoporation pit at jurassic production facility in sapriya kuwait oil company (k.s.c.)\nconstruction of solvent drain and storage foundation, thermal incinerator foundation, portal frame foundation and casting and placing of pipe sleepers at east raudhatain in koc\ntasks within this role included:\nco-ordinate all the related to concrete works associate with oil & gas pipe line"
  }
}