{
  "id": "cv (2305).pdf",
  "normalized_sections": {
    "ABOUT": "curriculum vitae\np.saravanan\nmennanthi (p.o)\nsathirakkudi (via)\nramanathapuram (dist)\ntamilnadu- india\nmobile: 09789104376\ne-mail:saran358 gmail.com\nelectrical b license holder b.no.b123562\n15 years experience in facility management, house wiring and o & m of electrical\nequipments, h.t., l.t., with b license holder (b.no.b123562).\neducational qualification\ncourse\n:\ns.s.l.c\ninstitute\n:\ngovernment high school, kamanottai..",
    "WORK EXPERIENCE": {
      "raw": "technical qualification\ncourse\n:\ni.t.i.electrician.(1997-1999).\ninstitute\n:\nmatha i.t.i., manamaduai.\ncompany\n:\nvariety services.(under wartsila india (p) ltd) .\nsince 2011 sep to till date.\ndesignation\n:\noperator.\nnature of job\no & m and trouble shooting of the following. 115/11kv,20/25mva power transformer 115/11kv,10/12.5mva power transformer 115/11kv substation, switchyard & sf6 breaker and vcb . 2x11kv/433v,630kva auxiliary transformers 3x8730kw wartsila gas engine with unic control system. lv system trouble shooting hv & lv breaker, maintenance. sensors calibration (pressure & temperature) vfd &compressors. company\n:\nlocal house wiring contractor\nfrom 2010 to 2011 sep.\ndesignation\n:\nelectrician\nnature of job\n1 and 3 wiring work in residential and commercial buildings.\nerection of service line connections, sb, ssb, pcc, mccb, lssb, ldb.\ncompany\n:\nimdaad llc - dubai.\nfrom dec.2005 to sep 2009\ndesignation\n:\nservice operative- electrical .\nnature of job\nsupervising the maintenance of service line connections, sb, ssb, pcc, mccb, lssb, ldb.\nsupervising the 1 and 3 lighting wiring. company\n:\nasmacs - dubai.\nfrom 2004 to dec 2005.\ndesignation\n:\nhelper- electrical .\nnature of job\nassists for maintenance of service line connections, sb, ssb, pcc, mccb, lssb, ldb.\nsupervising the 1 and 3 lighting wiring. company\n:\ncoffee day - madurai.\nfrom 2003 to 2004.\ndesignation\n:\nservice engineer .\nnature of job\nmaintenance and servicing of coffee vending machines. company\n:\ntnstc act apprentice training.\nfrom 2002 to 2003.\ndesignation\n:\napprentice(electrician) .\nnature of job\nmaintenance of bus and electrical appliances . company\n:\nlocal house wiring contractor\nfrom 2000 to 2002.\ndesignation\n:\nelectrician\nnature of job\n1 and 3 wiring work in residential and commercial buildings.\nerection of service line connections, sb, ssb, pcc, mccb, lssb, ldb..\npersonal details\nname\n:\np.saravanan\nfather s name\n:\ns.palaninathan\ndate of birth\n:\n29-05-1981\nsex\n:\nmale\nmarital status\n:\nmarried.\ncommunication address\n:\nmennanthi (p.o)\nsathirakkudi (via)\nramanathapuram (dist)\ntamilnadu- india\nnationality\n:\nindian\nlanguages known\n:\ntamil, english, hindi.& malayalam\npassport detail:\ndate of issue\n: 27/05/2015\ndate of expiry\n: 26/05/2025\ndeclaration\ni hereby declare that the given details are true to the best of my knowledge and belief.\nplace :\nyours sincerely,\ndate :\n(p.saravanan)",
      "companies": [
        "company",
        "inc",
        "ltd"
      ],
      "titles": [
        "engineer"
      ],
      "years": [
        "19",
        "20"
      ]
    }
  }
}