{
  "id": "cv (4971).pdf",
  "normalized_sections": {
    "SKILLS": [
      "analysis",
      "flutter",
      "haskell",
      "i am a junior developer currently working as a machine learning",
      "machine learning",
      "python",
      "sql"
    ],
    "WORK EXPERIENCE": {
      "raw": "engineer. i mark myself as a team player and leverage my knowledge\nmachine learning developer, aug 2018-till date",
      "companies": [],
      "titles": [
        "developer",
        "engineer"
      ],
      "years": [
        "20"
      ]
    },
    "PROJECTS": {
      "raw": "landscape classification using",
      "keywords": []
    },
    "EDUCATION": {
      "raw": "bachelor of technology from d&d university, daman and diu in 2018\ndata science course work - john hopkins university",
      "degree": [
        "bachelor"
      ],
      "institution": [
        "university"
      ],
      "years": [
        "20"
      ]
    }
  }
}