{
  "id": "cv (378).pdf",
  "normalized_sections": {
    "ABOUT": "curriculum vitae\nname arvind\naddress vill alapur\npost banpokhara\ndist mau (u.p)\npin code 221603\ncontact no.-09695245241\ne-mail arvindrajbhar602 gmail.com\nto achieve the best career which hence my in all the ways by\napplying my current knowledge\nacademic qualification :\nhigh school u.p. board in year 2008 with second div (50% marks)",
    "EDUCATION": {
      "raw": "intermediate from u.p. board in years 2010 first div (64%marks) one year diploma in electrical engineering services from board of indian technical society in 2011.\ntwo year diploma (i.t.i) in electrician from board of national",
      "degree": [],
      "institution": [],
      "years": [
        "20"
      ]
    },
    "WORK EXPERIENCE": {
      "raw": "council for vocational training in 2014.\nextra activies :\nnational certificate in modular employable . one year working experience with elentec india private limited from 10/02/2015 to 09/02/2016\npassport details :\npassport no. : n8163755 place of issue : lucknow date of issue : 24/02/2016 date of expiry : 23/02/2026",
      "companies": [],
      "titles": [],
      "years": [
        "20"
      ]
    },
    "SKILLS": [
      "10 march 1993",
      "arvind",
      "date of birth",
      "date: 16-05-2016",
      "english & hindi",
      "father s name",
      "male",
      "marital status",
      "personal details :",
      "place : delhi",
      "sex",
      "shri ram ashish",
      "unmarrid"
    ]
  }
}