{
  "id": "cv (4673).pdf",
  "normalized_sections": {
    "PROJECTS": {
      "raw": "construction consultant\nsupervised well site and location road construction, equipment procurement, and logistics.\ncoordinated facilities construction and well production.\nobtained, organized, and analyzed multiple subcontractor quotes across varying trades by specifying materials, identifying qualified\nsubcontractors, and negotiating prices.\nsupervised well site completions including: well site perforations, well site logging, and well site flow back.\nidentified and documented issues and risks to offer realistic recommendations for alternatives to achieve desired company results.\nheld and facilitated all daily jsa s.\nneeded.\n01/2010 to 01/2011\nprospective owner operator company name city , state\noversaw all front of the house and back of the house hiring and training.\nensured that front of the house shifts ran smoothly and efficiently while providing thorough and friendly customer service and driving sales in\na business averaging 100,000 in gross weekly sales.",
      "keywords": []
    },
    "WORK EXPERIENCE": {
      "raw": "operator.\n01/2011 to 01/2015\nconstruction consultant company name city , state",
      "companies": [
        "company"
      ],
      "titles": [],
      "years": [
        "20"
      ]
    },
    "EDUCATION": {
      "raw": "managed all front of the house and back of the house inventory control and purchasing.\n01/2007 to 01/2010\nassistant general manager company name city , state\nwrote and unified entire company wide inventory control system.\nmanaged daily cash intake, bar and alcohol inventory, building repair and maintenance budgets, and account payable.\noversaw hiring, training, and scheduling of all sixty front of the house employees.\n1990\nbusiness and civil engineering university of tennessee city business and civil engineering steve knowles kodiak energy consulting, llc -",
      "degree": [],
      "institution": [
        "university"
      ],
      "years": [
        "19",
        "20"
      ]
    },
    "SKILLS": [
      "budget",
      "budgets",
      "consulting",
      "customer service",
      "driving",
      "fast",
      "hiring",
      "inventory",
      "inventory control",
      "logging",
      "logistics",
      "materials",
      "microsoft office suite",
      "vice president of operations"
    ]
  }
}