{
  "id": "cv_24.pdf",
  "sections": {
    "ABOUT": "Dakota Johnson Technical Writer Technical Writer with proven experience delivering results in cross-functional teams. Skilled at solving real-world problems and building scalable solutions.",
    "SKILLS": "MongoDB, REST APIs, Selenium, Figma, CI/CD, Spring.",
    "WORK EXPERIENCE": "Coordinated machine learning models, improving performance and reliability; 2 year(s) of measurable impact. Managed internal tools, improving performance and reliability; 1 year(s) of measurable impact. Led machine learning models, improving performance and reliability; 4 year(s) of measurable impact. Implemented data pipelines, improving performance and reliability; 5 year(s) of measurable impact. Worked at FinPro from 2021 to 2026.",
    "EDUCATION": "B.Sc. in Computer Science from Stanford University, graduated 2017."
  }
}