{
  "id": "cv_272.pdf",
  "sections": {
    "ABOUT": "Morgan Hoang Financial Analyst Financial Analyst with proven experience delivering results in cross-functional teams. Skilled at solving real-world problems and building scalable solutions.",
    "SKILLS": "Power BI, Adobe Photoshop, JavaScript, React, JIRA, AWS, Computer Vision, Angular.",
    "WORK EXPERIENCE": "Managed analytics dashboards, improving performance and reliability; 1 year(s) of measurable impact. Led production services, improving performance and reliability; 2 year(s) of measurable impact. Worked at ABC Corp from 2019 to 2022.",
    "EDUCATION": "B.Sc. in Computer Science from MIT, graduated 2008."
  }
}