{"id": "cv (375).pdf", "sections": {"SKILLS": ": Flexibility, Communication and Problem solving.\n----------------------------------------------References---------------------------------------------------\n1)\nMr. Hashmukh Lalwala\nAdvocate (BCOM, LLB)\nSurat District Court, Surat\n +91- 98255 44224\n2)\nMr. Hiren Patel\nAssistant Professor (BE, MBA-Finance) \nS.R Luthra Institute of Management, Surat\n+91-98248 46424\n Chitrak Sawadiyawala\n (* Above mention Result is till 3rd semester and the Result of 4th semester is awaited)", "ABOUT": "Microsoft office, excel, word, PowerPoint, SPSS,TORA\n Operating systems used- windows, Android OS.\n \n-----------------------------------------", "PROJECTS": "Undertaken ------------------------------------------\n\nDid My Summer Internship for a period of two months from 5th June, 2014 to 17th July\n2014 in Surat Peoples Co-operative Bank in HR Department.\n\nDid my Comprehensive", "PROJECT": "for a Period of Eight Months From 1st August, 2014 to\n21st April, 2015 in Shree Ram Krishna Exports Pvt. Ltd. in HR Department.\n\n Did Global Country Study Report on Business Opportunities of Chakradhar\nAutomobile in Venezuela as a part of GTU Curriculum. \n---------------------------------------------- Achievements-------------------------------------------------\n\nAttained the 13th Annual Conference on Technology and HR Conducted by\nAhmadabad Management Association.\n\nGot a Certificate and Trophy from my Cast On behalf of More than 60% in BCOM.\n---------------------------------------------Personal Dossier-----------------------------------------------\n\nDate of Birth: 11th October 1992\n\nPermanent Address: C/4, Shree Sai Jalaram Society, Nr. Chandradeep Society,\nUdhna, Surat, Gujarat.\n\nLanguage Known: English, Hindi, Gujarati.\n\nHobbies/Interests: Web Surfing, Reading and Social Networking Sites."}}