{"id": "cv (5017).pdf", "sections": {"ACTIVITIES": "IBM data Analytics.", "PROJECTS": "Text Analysis of", "PROJECT": "report.", "SKILLS": "Data Analysis, Data Mining, Data Modeling,\nData Processing, Machine Learning,\nNatural Language Processing, Artificial\nIntelligence, Statistics. SQL, Tableau,\nPowerBI.", "WORK EXPERIENCE": "TUC \nData Analyst, Jan 2018 - Nov 2020 \nCreation of dashboards using SQL. Used to write SQL queries for the\ncompany to bring out the solution required. Used to bring out insights\nfrom the data using visualisation tools like Tableau and Power BI.", "EDUCATION": "BCA Bhimrao Sen College, Jharkhand, 2018"}}