{"id": "cv (3372).pdf", "sections": {"SKILLS": ":\nWeb Design\nPHP, MySQL, HTML,CSS,Javascript.\nLanguage", "SKILL": ", Excellent Grasping \nPower\nI hereby declare that the information furnished above is true to the best of my \nknowledge.\nPlace: pune \nDate: 31-7-2015 \n(Puja S. Deshmukh)", "PROJECT": "contains \nmodules like Transaction, Reporting, Customer order & \nproduct etc.", "ACTIVITIES": "Requirement Analysis and design\nDeveloped customer module using Php\nDesigned Test cases, Bug report Test data and Issue \nregister.\nTeam Size\n2\nPersonal Details:\nFull Name\nPuja Shriniwas Deshmukh\nDate of Birth\n12th April 1992\nMarital Status \nSingle \nContact Address\nSamartha Society Bibawewadi Pune\nLanguages Known\nEnglish, Hindi, Marathi. \nContact Number\n8007042632,8862003386\nEmail\ndeshmukhpooja007@gmail.com\nHobbies\nTraveling, Playing Badmintan, Writing\nStrengths\nConfidence, Good Communication"}}