{"id": "cv (4342).pdf", "sections": {"SKILLS": "Additional Information\nWilling to relocate: Anywhere Authorized to work in the US for any employer\nLINKS https://www.linkedin.com/in/jesi-crane-53995933", "ACTIVITIES": ".\nDemonstrate excellent oral and written communication", "ABOUT": "flights,\naircraft, weather, travel routes and services, arrival times, and/or schedules.\nAssist passengers while entering or disembarking the aircraft.\nAssist passengers in placing carry- on luggage in overhead, garment, or under-seat storage.\nTrained and mentored new flight attendants; Participating in training programs organized by company and provide update on all techniques\nrelevant to safety.\nMaintained high level of personal decorum and professional conduct while in uniform.\nOperate audio and video systems.\nWilling to relocate: Anywhere"}}