{"id": "cv (4961).pdf", "sections": {"WORK EXPERIENCE": "", "EDUCATION": "ROBERT MATHEWS\nMACHINE LEARNING ENGINEER (QUALITY CONTROL)\nRecent Graduate testing and debugging machine learning models. I have worked on multiple", "PROJECTS": "and have\ncontributed to the testing and quality control of models over time. I am looking to switch to a development role where I can\nexercise my", "SKILLS": "Data manipulation and Code update for\nEmployee turnover Prediction using\nRandom Forest. \nSelenium Tester - Level B", "ABOUT": "", "PROJECT": "OTHER QUALIFICATION"}}