{"id": "cv (531).pdf", "sections": {"PROJECT": "data base by writing computer programs; entering and backing up data.\n\nMaintains product and company reputation by complying with federal and state regulations.\n\nContributes to team effort by accomplishing related results as needed.\nAcademic Qualification:\n\nBE- Electrical and Electronics Engineering (2007-2010)\nSree Sowdambika College of Engineering (65%), Anna University\n\nDiploma in Electrical and Electronics Engineering (2004-2007)\nArulmegu Kalashalingam Polytechnic College (64.62%)\nComputer Knowledge:\n\nExcellent Experience in using Windows Operating System. \n\nExcellent experience in using MS office.\n\nGood Experience in MATLAB, Power system Analysis tool box \n \nPersonal Profile\n\nName\n - \nR.Siva\n\nFather Name \n - \nMr.S.Ramaraj\n\nLanguages Known - \nTamil, English.\n\nMarital status \n - \nUnmarried \n\nPass port number\n - \nJ0616625\n\nDate of issue \n - \n24/05/2010\n\nDate of expiry \n - \n23/05/2020\n\nSkype Id\n - avis7289\n\nAddress\n -\n90/1B, Koonankulam North Street ,\nSrivilliputtur  626125, Tamilnadu, India\nDeclaration\nI hereby declare that all the above stated information is true and correct to the best of my\nknowledge and belief.\n \nSiva Ramaraj", "PROJECTS": ".\n\nTo Improve the power quality and also Mitigate the harmonics with help of Filters\n(Capacitive)\n\nTo analysis the power quality problems used in Fluke Device 2.0 \nRamco Cements  Tirunelveli", "ACTIVITIES": "; resolving\nproblems.\n\nControls"}}